{
  "mode": "profile-only",
  "serverUrl": "ws://127.0.0.1:6912",
  "headless": true,
  "simOnly": true,
  "movementPollMs": 120,
  "requestedCaptureMs": 5000,
  "actualCaptureMs": 5419,
  "loopIterations": 40,
  "approxLoopHz": 7.38,
  "files": {
    "node": "C:\\Users\\Main\\OneDrive\\Desktop\\vibe-coded-3d-browser-game\\profiling\\multiplayer-e2e\\capture-2026-02-23T05-16-25-835Z-node.cpuprofile",
    "browserA": "C:\\Users\\Main\\OneDrive\\Desktop\\vibe-coded-3d-browser-game\\profiling\\multiplayer-e2e\\capture-2026-02-23T05-16-25-835Z-browser-a.cpuprofile",
    "browserB": "C:\\Users\\Main\\OneDrive\\Desktop\\vibe-coded-3d-browser-game\\profiling\\multiplayer-e2e\\capture-2026-02-23T05-16-25-835Z-browser-b.cpuprofile"
  }
}